{
  "parent": "minecraft:recipes/root",
  "rewards": {
    "recipes": [
	    "litesilverwolfsbuildingblocks:brown_clay_ball"
		]
  },
  "criteria": {
    "has_brown_clay": {
      "trigger": "minecraft:inventory_changed",
      "conditions": {
        "items": [
          {
            "item": "litesilverwolfsbuildingblocks:brown_clay"
          }
        ]
      }
    },
	"has_the_recipe": {
      "trigger": "minecraft:recipe_unlocked",
      "conditions": {
        "recipe": "litesilverwolfsbuildingblocks:brown_clay_ball"
      }
    }
  },
  "requirements": [
    [
      "has_brown_clay",
      "has_the_recipe"
    ]
  ]
}