{
  "parent": "minecraft:recipes/root",
  "rewards": {
    "recipes": [
	    "silverwolfsbuildingblocks:black_birch_log",
		"silverwolfsbuildingblocks:blue_birch_log",
		"silverwolfsbuildingblocks:brown_birch_log",
		"silverwolfsbuildingblocks:cyan_birch_log",
		"silverwolfsbuildingblocks:gray_birch_log",
		"silverwolfsbuildingblocks:green_birch_log",
		"silverwolfsbuildingblocks:light_blue_birch_log",
		"silverwolfsbuildingblocks:light_gray_birch_log",
		"silverwolfsbuildingblocks:lime_birch_log",
		"silverwolfsbuildingblocks:magenta_birch_log",
		"silverwolfsbuildingblocks:orange_birch_log",
		"silverwolfsbuildingblocks:pink_birch_log",
		"silverwolfsbuildingblocks:purple_birch_log",
		"silverwolfsbuildingblocks:red_birch_log",
		"silverwolfsbuildingblocks:white_birch_log",
		"silverwolfsbuildingblocks:yellow_birch_log"
		]
  },
  "criteria": {
    "has_birch_log": {
      "trigger": "minecraft:inventory_changed",
      "conditions": {
        "items": [
          {
            "item": "minecraft:birch_log"
          }
        ]
      }
    },
	"has_the_recipe": {
      "trigger": "minecraft:recipe_unlocked",
      "conditions": {
        "recipe": "silverwolfsbuildingblocks:black_birch_log"
      }
    }
  },
  "requirements": [
    [
      "has_birch_log",
      "has_the_recipe"
    ]
  ]
}