{
  "parent": "minecraft:recipes/root",
  "rewards": {
    "recipes": [
      "silverwolfsbuildingblocks:white_jungle_ladder",
      "silverwolfsbuildingblocks:white_jungle_fence",
      "silverwolfsbuildingblocks:white_jungle_fence_gate"
    ]
  },
  "criteria": {
    "has_white_jungle_sticks": {
      "trigger": "minecraft:inventory_changed",
      "conditions": {
        "items": [
          {
            "item": "silverwolfsbuildingblocks:white_jungle_stick"
          }
        ]
      }
    },
    "has_the_recipe": {
      "trigger": "minecraft:recipe_unlocked",
      "conditions": {
        "recipe": "silverwolfsbuildingblocks:white_jungle_ladder"
      }
    }
  },
  "requirements": [
    [
      "has_white_jungle_sticks",
      "has_the_recipe"
    ]
  ]
}